Compiled from "PortalFrameBlockEntity.java"
public class io.redspace.ironsspellbooks.block.portal_frame.PortalFrameBlockEntity extends net.minecraft.world.level.block.entity.BlockEntity {
  private io.redspace.ironsspellbooks.block.portal_frame.PortalFrameBlockEntity$PortalId portalId;

  private int color;

  private java.util.UUID ownerUUID;

  boolean clientIsConnected;

  private boolean active;

  private int activeCooldown;

  public io.redspace.ironsspellbooks.block.portal_frame.PortalFrameBlockEntity(net.minecraft.core.BlockPos, net.minecraft.world.level.block.state.BlockState);
    Code:
       0: aload_0
       1: getstatic     #7                  // Field io/redspace/ironsspellbooks/registries/BlockRegistry.PORTAL_FRAME_BLOCK_ENTITY:Lnet/neoforged/neoforge/registries/DeferredHolder;
       4: invokevirtual #13                 // Method net/neoforged/neoforge/registries/DeferredHolder.get:()Ljava/lang/Object;
       7: checkcast     #19                 // class net/minecraft/world/level/block/entity/BlockEntityType
      10: aload_1
      11: aload_2
      12: invokespecial #21                 // Method "<init>":(Lnet/minecraft/world/level/block/entity/BlockEntityType;Lnet/minecraft/core/BlockPos;Lnet/minecraft/world/level/block/state/BlockState;)V
      15: return

  public io.redspace.ironsspellbooks.block.portal_frame.PortalFrameBlockEntity(net.minecraft.world.level.block.entity.BlockEntityType<?>, net.minecraft.core.BlockPos, net.minecraft.world.level.block.state.BlockState);
    Code:
       0: aload_0
       1: aload_1
       2: aload_2
       3: aload_3
       4: invokespecial #25                 // Method net/minecraft/world/level/block/entity/BlockEntity."<init>":(Lnet/minecraft/world/level/block/entity/BlockEntityType;Lnet/minecraft/core/BlockPos;Lnet/minecraft/world/level/block/state/BlockState;)V
       7: aload_0
       8: iconst_m1
       9: putfield      #28                 // Field color:I
      12: aload_0
      13: aconst_null
      14: putfield      #32                 // Field ownerUUID:Ljava/util/UUID;
      17: aload_3
      18: invokestatic  #36                 // Method isPrimary:(Lnet/minecraft/world/level/block/state/BlockState;)Z
      21: ifeq          44
      24: aload_0
      25: new           #40                 // class io/redspace/ironsspellbooks/block/portal_frame/PortalFrameBlockEntity$PortalId
      28: dup
      29: invokestatic  #42                 // Method java/util/UUID.randomUUID:()Ljava/util/UUID;
      32: invokestatic  #48                 // Method java/util/Optional.of:(Ljava/lang/Object;)Ljava/util/Optional;
      35: invokespecial #54                 // Method io/redspace/ironsspellbooks/block/portal_frame/PortalFrameBlockEntity$PortalId."<init>":(Ljava/util/Optional;)V
      38: putfield      #57                 // Field portalId:Lio/redspace/ironsspellbooks/block/portal_frame/PortalFrameBlockEntity$PortalId;
      41: goto          58
      44: aload_0
      45: new           #40                 // class io/redspace/ironsspellbooks/block/portal_frame/PortalFrameBlockEntity$PortalId
      48: dup
      49: invokestatic  #61                 // Method java/util/Optional.empty:()Ljava/util/Optional;
      52: invokespecial #54                 // Method io/redspace/ironsspellbooks/block/portal_frame/PortalFrameBlockEntity$PortalId."<init>":(Ljava/util/Optional;)V
      55: putfield      #57                 // Field portalId:Lio/redspace/ironsspellbooks/block/portal_frame/PortalFrameBlockEntity$PortalId;
      58: return

  public static boolean isPrimary(net.minecraft.world.level.block.state.BlockState);
    Code:
       0: aload_0
       1: getstatic     #65                 // Field io/redspace/ironsspellbooks/block/portal_frame/PortalFrameBlock.HALF:Lnet/minecraft/world/level/block/state/properties/EnumProperty;
       4: invokevirtual #71                 // Method net/minecraft/world/level/block/state/BlockState.getValue:(Lnet/minecraft/world/level/block/state/properties/Property;)Ljava/lang/Comparable;
       7: checkcast     #77                 // class net/minecraft/world/level/block/state/properties/DoubleBlockHalf
      10: getstatic     #79                 // Field net/minecraft/world/level/block/state/properties/DoubleBlockHalf.LOWER:Lnet/minecraft/world/level/block/state/properties/DoubleBlockHalf;
      13: invokevirtual #83                 // Method net/minecraft/world/level/block/state/properties/DoubleBlockHalf.equals:(Ljava/lang/Object;)Z
      16: ireturn

  private void ifNeighborPresent(java.util.function.Consumer<io.redspace.ironsspellbooks.block.portal_frame.PortalFrameBlockEntity>);
    Code:
       0: aload_0
       1: getfield      #1                  // Field level:Lnet/minecraft/world/level/Level;
       4: ifnull        57
       7: aload_0
       8: getfield      #1                  // Field level:Lnet/minecraft/world/level/Level;
      11: aload_0
      12: invokevirtual #87                 // Method getBlockPos:()Lnet/minecraft/core/BlockPos;
      15: aload_0
      16: invokevirtual #91                 // Method getBlockState:()Lnet/minecraft/world/level/block/state/BlockState;
      19: getstatic     #65                 // Field io/redspace/ironsspellbooks/block/portal_frame/PortalFrameBlock.HALF:Lnet/minecraft/world/level/block/state/properties/EnumProperty;
      22: invokevirtual #71                 // Method net/minecraft/world/level/block/state/BlockState.getValue:(Lnet/minecraft/world/level/block/state/properties/Property;)Ljava/lang/Comparable;
      25: checkcast     #77                 // class net/minecraft/world/level/block/state/properties/DoubleBlockHalf
      28: invokevirtual #95                 // Method net/minecraft/world/level/block/state/properties/DoubleBlockHalf.getDirectionToOther:()Lnet/minecraft/core/Direction;
      31: invokevirtual #99                 // Method net/minecraft/core/BlockPos.relative:(Lnet/minecraft/core/Direction;)Lnet/minecraft/core/BlockPos;
      34: invokevirtual #105                // Method net/minecraft/world/level/Level.getBlockEntity:(Lnet/minecraft/core/BlockPos;)Lnet/minecraft/world/level/block/entity/BlockEntity;
      37: astore_2
      38: aload_2
      39: instanceof    #2                  // class io/redspace/ironsspellbooks/block/portal_frame/PortalFrameBlockEntity
      42: ifeq          57
      45: aload_2
      46: checkcast     #2                  // class io/redspace/ironsspellbooks/block/portal_frame/PortalFrameBlockEntity
      49: astore_3
      50: aload_1
      51: aload_3
      52: invokeinterface #111,  2          // InterfaceMethod java/util/function/Consumer.accept:(Ljava/lang/Object;)V
      57: return

  private <T> T ifNeighborPresentExecute(java.util.function.Function<io.redspace.ironsspellbooks.block.portal_frame.PortalFrameBlockEntity, T>, T);
    Code:
       0: aload_0
       1: getfield      #1                  // Field level:Lnet/minecraft/world/level/Level;
       4: ifnull        60
       7: aload_0
       8: getfield      #1                  // Field level:Lnet/minecraft/world/level/Level;
      11: aload_0
      12: invokevirtual #87                 // Method getBlockPos:()Lnet/minecraft/core/BlockPos;
      15: aload_0
      16: invokevirtual #91                 // Method getBlockState:()Lnet/minecraft/world/level/block/state/BlockState;
      19: getstatic     #65                 // Field io/redspace/ironsspellbooks/block/portal_frame/PortalFrameBlock.HALF:Lnet/minecraft/world/level/block/state/properties/EnumProperty;
      22: invokevirtual #71                 // Method net/minecraft/world/level/block/state/BlockState.getValue:(Lnet/minecraft/world/level/block/state/properties/Property;)Ljava/lang/Comparable;
      25: checkcast     #77                 // class net/minecraft/world/level/block/state/properties/DoubleBlockHalf
      28: invokevirtual #95                 // Method net/minecraft/world/level/block/state/properties/DoubleBlockHalf.getDirectionToOther:()Lnet/minecraft/core/Direction;
      31: invokevirtual #99                 // Method net/minecraft/core/BlockPos.relative:(Lnet/minecraft/core/Direction;)Lnet/minecraft/core/BlockPos;
      34: invokevirtual #105                // Method net/minecraft/world/level/Level.getBlockEntity:(Lnet/minecraft/core/BlockPos;)Lnet/minecraft/world/level/block/entity/BlockEntity;
      37: astore_3
      38: aload_3
      39: instanceof    #2                  // class io/redspace/ironsspellbooks/block/portal_frame/PortalFrameBlockEntity
      42: ifeq          60
      45: aload_3
      46: checkcast     #2                  // class io/redspace/ironsspellbooks/block/portal_frame/PortalFrameBlockEntity
      49: astore        4
      51: aload_1
      52: aload         4
      54: invokeinterface #117,  2          // InterfaceMethod java/util/function/Function.apply:(Ljava/lang/Object;)Ljava/lang/Object;
      59: areturn
      60: aload_2
      61: areturn

  private void ifOtherPortalFramePresent(java.util.function.Consumer<io.redspace.ironsspellbooks.block.portal_frame.PortalFrameBlockEntity>);
    Code:
       0: aload_0
       1: invokevirtual #123                // Method getPortalData:()Lio/redspace/ironsspellbooks/entity/spells/portal/PortalData;
       4: astore_2
       5: aload_2
       6: ifnull        125
       9: aload_0
      10: getfield      #1                  // Field level:Lnet/minecraft/world/level/Level;
      13: astore        4
      15: aload         4
      17: instanceof    #127                // class net/minecraft/server/level/ServerLevel
      20: ifeq          125
      23: aload         4
      25: checkcast     #127                // class net/minecraft/server/level/ServerLevel
      28: astore_3
      29: aload_3
      30: invokevirtual #129                // Method net/minecraft/server/level/ServerLevel.getServer:()Lnet/minecraft/server/MinecraftServer;
      33: astore        4
      35: aload_0
      36: invokevirtual #133                // Method getUUID:()Ljava/util/UUID;
      39: aload_2
      40: getfield      #136                // Field io/redspace/ironsspellbooks/entity/spells/portal/PortalData.portalEntityId1:Ljava/util/UUID;
      43: invokevirtual #141                // Method java/util/UUID.equals:(Ljava/lang/Object;)Z
      46: istore        5
      48: iload         5
      50: ifeq          60
      53: aload_2
      54: getfield      #142                // Field io/redspace/ironsspellbooks/entity/spells/portal/PortalData.globalPos2:Lio/redspace/ironsspellbooks/entity/spells/portal/PortalPos;
      57: goto          64
      60: aload_2
      61: getfield      #146                // Field io/redspace/ironsspellbooks/entity/spells/portal/PortalData.globalPos1:Lio/redspace/ironsspellbooks/entity/spells/portal/PortalPos;
      64: astore        6
      66: aload         4
      68: aload         6
      70: invokevirtual #149                // Method io/redspace/ironsspellbooks/entity/spells/portal/PortalPos.dimension:()Lnet/minecraft/resources/ResourceKey;
      73: invokevirtual #155                // Method net/minecraft/server/MinecraftServer.getLevel:(Lnet/minecraft/resources/ResourceKey;)Lnet/minecraft/server/level/ServerLevel;
      76: astore        7
      78: aload         6
      80: invokevirtual #161                // Method io/redspace/ironsspellbooks/entity/spells/portal/PortalPos.pos:()Lnet/minecraft/world/phys/Vec3;
      83: invokestatic  #165                // Method net/minecraft/core/BlockPos.containing:(Lnet/minecraft/core/Position;)Lnet/minecraft/core/BlockPos;
      86: astore        8
      88: aload         7
      90: ifnull        125
      93: aload         7
      95: aload         8
      97: invokevirtual #169                // Method net/minecraft/server/level/ServerLevel.getBlockEntity:(Lnet/minecraft/core/BlockPos;)Lnet/minecraft/world/level/block/entity/BlockEntity;
     100: astore        10
     102: aload         10
     104: instanceof    #2                  // class io/redspace/ironsspellbooks/block/portal_frame/PortalFrameBlockEntity
     107: ifeq          125
     110: aload         10
     112: checkcast     #2                  // class io/redspace/ironsspellbooks/block/portal_frame/PortalFrameBlockEntity
     115: astore        9
     117: aload_1
     118: aload         9
     120: invokeinterface #111,  2          // InterfaceMethod java/util/function/Consumer.accept:(Ljava/lang/Object;)V
     125: return

  public boolean isPortalConnected();
    Code:
       0: aload_0
       1: invokevirtual #123                // Method getPortalData:()Lio/redspace/ironsspellbooks/entity/spells/portal/PortalData;
       4: ifnull        11
       7: iconst_1
       8: goto          12
      11: iconst_0
      12: ireturn

  public void breakPortalConnection();
    Code:
       0: aload_0
       1: iconst_m1
       2: invokevirtual #170                // Method setColor:(I)V
       5: aload_0
       6: invokevirtual #123                // Method getPortalData:()Lio/redspace/ironsspellbooks/entity/spells/portal/PortalData;
       9: astore_1
      10: aload_1
      11: ifnull        47
      14: getstatic     #174                // Field io/redspace/ironsspellbooks/capabilities/magic/PortalManager.INSTANCE:Lio/redspace/ironsspellbooks/capabilities/magic/PortalManager;
      17: aload_1
      18: getfield      #136                // Field io/redspace/ironsspellbooks/entity/spells/portal/PortalData.portalEntityId1:Ljava/util/UUID;
      21: invokevirtual #180                // Method io/redspace/ironsspellbooks/capabilities/magic/PortalManager.removePortalData:(Ljava/util/UUID;)V
      24: getstatic     #174                // Field io/redspace/ironsspellbooks/capabilities/magic/PortalManager.INSTANCE:Lio/redspace/ironsspellbooks/capabilities/magic/PortalManager;
      27: aload_1
      28: getfield      #184                // Field io/redspace/ironsspellbooks/entity/spells/portal/PortalData.portalEntityId2:Ljava/util/UUID;
      31: invokevirtual #180                // Method io/redspace/ironsspellbooks/capabilities/magic/PortalManager.removePortalData:(Ljava/util/UUID;)V
      34: aload_0
      35: invokedynamic #187,  0            // InvokeDynamic #0:accept:()Ljava/util/function/Consumer;
      40: invokevirtual #190                // Method ifOtherPortalFramePresent:(Ljava/util/function/Consumer;)V
      43: aload_0
      44: invokevirtual #194                // Method setChanged:()V
      47: return

  private io.redspace.ironsspellbooks.entity.spells.portal.PortalData getPortalData();
    Code:
       0: getstatic     #174                // Field io/redspace/ironsspellbooks/capabilities/magic/PortalManager.INSTANCE:Lio/redspace/ironsspellbooks/capabilities/magic/PortalManager;
       3: aload_0
       4: getfield      #57                 // Field portalId:Lio/redspace/ironsspellbooks/block/portal_frame/PortalFrameBlockEntity$PortalId;
       7: aload_0
       8: invokevirtual #198                // Method io/redspace/ironsspellbooks/block/portal_frame/PortalFrameBlockEntity$PortalId.uuid:(Lio/redspace/ironsspellbooks/block/portal_frame/PortalFrameBlockEntity;)Ljava/util/UUID;
      11: invokevirtual #202                // Method io/redspace/ironsspellbooks/capabilities/magic/PortalManager.getPortalData:(Ljava/util/UUID;)Lio/redspace/ironsspellbooks/entity/spells/portal/PortalData;
      14: areturn

  public net.minecraft.world.phys.Vec3 getPortalLocation();
    Code:
       0: aload_0
       1: invokevirtual #91                 // Method getBlockState:()Lnet/minecraft/world/level/block/state/BlockState;
       4: invokestatic  #36                 // Method isPrimary:(Lnet/minecraft/world/level/block/state/BlockState;)Z
       7: ifeq          18
      10: aload_0
      11: invokevirtual #87                 // Method getBlockPos:()Lnet/minecraft/core/BlockPos;
      14: invokevirtual #205                // Method net/minecraft/core/BlockPos.getBottomCenter:()Lnet/minecraft/world/phys/Vec3;
      17: areturn
      18: aload_0
      19: invokevirtual #87                 // Method getBlockPos:()Lnet/minecraft/core/BlockPos;
      22: invokevirtual #205                // Method net/minecraft/core/BlockPos.getBottomCenter:()Lnet/minecraft/world/phys/Vec3;
      25: dconst_0
      26: dconst_1
      27: dconst_0
      28: invokevirtual #208                // Method net/minecraft/world/phys/Vec3.subtract:(DDD)Lnet/minecraft/world/phys/Vec3;
      31: areturn

  public java.util.UUID getOwnerUUID();
    Code:
       0: aload_0
       1: invokevirtual #91                 // Method getBlockState:()Lnet/minecraft/world/level/block/state/BlockState;
       4: invokestatic  #36                 // Method isPrimary:(Lnet/minecraft/world/level/block/state/BlockState;)Z
       7: ifeq          15
      10: aload_0
      11: getfield      #32                 // Field ownerUUID:Ljava/util/UUID;
      14: areturn
      15: aload_0
      16: invokedynamic #214,  0            // InvokeDynamic #1:apply:()Ljava/util/function/Function;
      21: aconst_null
      22: invokevirtual #217                // Method ifNeighborPresentExecute:(Ljava/util/function/Function;Ljava/lang/Object;)Ljava/lang/Object;
      25: checkcast     #43                 // class java/util/UUID
      28: areturn

  public void setOwnerUUID(java.util.UUID);
    Code:
       0: aload_0
       1: invokevirtual #91                 // Method getBlockState:()Lnet/minecraft/world/level/block/state/BlockState;
       4: invokestatic  #36                 // Method isPrimary:(Lnet/minecraft/world/level/block/state/BlockState;)Z
       7: ifeq          18
      10: aload_0
      11: aload_1
      12: putfield      #32                 // Field ownerUUID:Ljava/util/UUID;
      15: goto          28
      18: aload_0
      19: aload_1
      20: invokedynamic #221,  0            // InvokeDynamic #2:accept:(Ljava/util/UUID;)Ljava/util/function/Consumer;
      25: invokevirtual #224                // Method ifNeighborPresent:(Ljava/util/function/Consumer;)V
      28: return

  public void teleport(net.minecraft.world.entity.Entity);
    Code:
       0: aload_1
       1: getfield      #227                // Field net/minecraft/world/entity/Entity.level:Lnet/minecraft/world/level/Level;
       4: astore_3
       5: aload_3
       6: instanceof    #127                // class net/minecraft/server/level/ServerLevel
       9: ifeq          79
      12: aload_3
      13: checkcast     #127                // class net/minecraft/server/level/ServerLevel
      16: astore_2
      17: aload_0
      18: invokevirtual #133                // Method getUUID:()Ljava/util/UUID;
      21: astore_3
      22: getstatic     #174                // Field io/redspace/ironsspellbooks/capabilities/magic/PortalManager.INSTANCE:Lio/redspace/ironsspellbooks/capabilities/magic/PortalManager;
      25: aload_3
      26: aload_1
      27: invokevirtual #230                // Method net/minecraft/world/entity/Entity.getUUID:()Ljava/util/UUID;
      30: iconst_1
      31: invokevirtual #231                // Method io/redspace/ironsspellbooks/capabilities/magic/PortalManager.processDelayCooldown:(Ljava/util/UUID;Ljava/util/UUID;I)V
      34: getstatic     #174                // Field io/redspace/ironsspellbooks/capabilities/magic/PortalManager.INSTANCE:Lio/redspace/ironsspellbooks/capabilities/magic/PortalManager;
      37: aload_3
      38: aload_1
      39: invokevirtual #235                // Method io/redspace/ironsspellbooks/capabilities/magic/PortalManager.canUsePortal:(Ljava/util/UUID;Lnet/minecraft/world/entity/Entity;)Z
      42: ifeq          79
      45: getstatic     #174                // Field io/redspace/ironsspellbooks/capabilities/magic/PortalManager.INSTANCE:Lio/redspace/ironsspellbooks/capabilities/magic/PortalManager;
      48: aload_3
      49: invokevirtual #202                // Method io/redspace/ironsspellbooks/capabilities/magic/PortalManager.getPortalData:(Ljava/util/UUID;)Lio/redspace/ironsspellbooks/entity/spells/portal/PortalData;
      52: astore        4
      54: getstatic     #174                // Field io/redspace/ironsspellbooks/capabilities/magic/PortalManager.INSTANCE:Lio/redspace/ironsspellbooks/capabilities/magic/PortalManager;
      57: aload_1
      58: aload_3
      59: invokevirtual #239                // Method io/redspace/ironsspellbooks/capabilities/magic/PortalManager.addPortalCooldown:(Lnet/minecraft/world/entity/Entity;Ljava/util/UUID;)V
      62: aload         4
      64: aload_3
      65: invokevirtual #243                // Method io/redspace/ironsspellbooks/entity/spells/portal/PortalData.getConnectedPortalPos:(Ljava/util/UUID;)Ljava/util/Optional;
      68: aload_0
      69: aload_2
      70: aload_1
      71: invokedynamic #247,  0            // InvokeDynamic #3:accept:(Lio/redspace/ironsspellbooks/block/portal_frame/PortalFrameBlockEntity;Lnet/minecraft/server/level/ServerLevel;Lnet/minecraft/world/entity/Entity;)Ljava/util/function/Consumer;
      76: invokevirtual #250                // Method java/util/Optional.ifPresent:(Ljava/util/function/Consumer;)V
      79: return

  protected void loadAdditional(net.minecraft.nbt.CompoundTag, net.minecraft.core.HolderLookup$Provider);
    Code:
       0: aload_0
       1: aload_1
       2: aload_2
       3: invokespecial #253                // Method net/minecraft/world/level/block/entity/BlockEntity.loadAdditional:(Lnet/minecraft/nbt/CompoundTag;Lnet/minecraft/core/HolderLookup$Provider;)V
       6: aload_1
       7: ldc_w         #257                // String uuid
      10: invokevirtual #258                // Method net/minecraft/nbt/CompoundTag.contains:(Ljava/lang/String;)Z
      13: ifeq          39
      16: aload_1
      17: ldc_w         #257                // String uuid
      20: invokevirtual #264                // Method net/minecraft/nbt/CompoundTag.getUUID:(Ljava/lang/String;)Ljava/util/UUID;
      23: astore_3
      24: aload_0
      25: new           #40                 // class io/redspace/ironsspellbooks/block/portal_frame/PortalFrameBlockEntity$PortalId
      28: dup
      29: aload_3
      30: invokestatic  #48                 // Method java/util/Optional.of:(Ljava/lang/Object;)Ljava/util/Optional;
      33: invokespecial #54                 // Method io/redspace/ironsspellbooks/block/portal_frame/PortalFrameBlockEntity$PortalId."<init>":(Ljava/util/Optional;)V
      36: putfield      #57                 // Field portalId:Lio/redspace/ironsspellbooks/block/portal_frame/PortalFrameBlockEntity$PortalId;
      39: aload_1
      40: ldc_w         #267                // String owner
      43: invokevirtual #258                // Method net/minecraft/nbt/CompoundTag.contains:(Ljava/lang/String;)Z
      46: ifeq          60
      49: aload_0
      50: aload_1
      51: ldc_w         #267                // String owner
      54: invokevirtual #264                // Method net/minecraft/nbt/CompoundTag.getUUID:(Ljava/lang/String;)Ljava/util/UUID;
      57: putfield      #32                 // Field ownerUUID:Ljava/util/UUID;
      60: aload_1
      61: ldc_w         #269                // String color
      64: invokevirtual #258                // Method net/minecraft/nbt/CompoundTag.contains:(Ljava/lang/String;)Z
      67: ifeq          81
      70: aload_0
      71: aload_1
      72: ldc_w         #269                // String color
      75: invokevirtual #270                // Method net/minecraft/nbt/CompoundTag.getInt:(Ljava/lang/String;)I
      78: putfield      #28                 // Field color:I
      81: return

  protected void saveAdditional(net.minecraft.nbt.CompoundTag, net.minecraft.core.HolderLookup$Provider);
    Code:
       0: aload_0
       1: aload_1
       2: aload_2
       3: invokespecial #274                // Method net/minecraft/world/level/block/entity/BlockEntity.saveAdditional:(Lnet/minecraft/nbt/CompoundTag;Lnet/minecraft/core/HolderLookup$Provider;)V
       6: aload_0
       7: invokevirtual #91                 // Method getBlockState:()Lnet/minecraft/world/level/block/state/BlockState;
      10: invokestatic  #36                 // Method isPrimary:(Lnet/minecraft/world/level/block/state/BlockState;)Z
      13: ifeq          62
      16: aload_1
      17: ldc_w         #269                // String color
      20: aload_0
      21: getfield      #28                 // Field color:I
      24: invokevirtual #277                // Method net/minecraft/nbt/CompoundTag.putInt:(Ljava/lang/String;I)V
      27: aload_0
      28: invokevirtual #133                // Method getUUID:()Ljava/util/UUID;
      31: astore_3
      32: aload_3
      33: ifnull        44
      36: aload_1
      37: ldc_w         #257                // String uuid
      40: aload_3
      41: invokevirtual #281                // Method net/minecraft/nbt/CompoundTag.putUUID:(Ljava/lang/String;Ljava/util/UUID;)V
      44: aload_0
      45: getfield      #32                 // Field ownerUUID:Ljava/util/UUID;
      48: ifnull        62
      51: aload_1
      52: ldc_w         #267                // String owner
      55: aload_0
      56: getfield      #32                 // Field ownerUUID:Ljava/util/UUID;
      59: invokevirtual #281                // Method net/minecraft/nbt/CompoundTag.putUUID:(Ljava/lang/String;Ljava/util/UUID;)V
      62: return

  public java.util.UUID getUUID();
    Code:
       0: aload_0
       1: getfield      #57                 // Field portalId:Lio/redspace/ironsspellbooks/block/portal_frame/PortalFrameBlockEntity$PortalId;
       4: aload_0
       5: invokevirtual #198                // Method io/redspace/ironsspellbooks/block/portal_frame/PortalFrameBlockEntity$PortalId.uuid:(Lio/redspace/ironsspellbooks/block/portal_frame/PortalFrameBlockEntity;)Ljava/util/UUID;
       8: areturn

  public net.minecraft.nbt.CompoundTag getUpdateTag(net.minecraft.core.HolderLookup$Provider);
    Code:
       0: aload_0
       1: aload_1
       2: invokespecial #285                // Method net/minecraft/world/level/block/entity/BlockEntity.getUpdateTag:(Lnet/minecraft/core/HolderLookup$Provider;)Lnet/minecraft/nbt/CompoundTag;
       5: astore_2
       6: aload_2
       7: ldc_w         #289                // String connected
      10: aload_0
      11: invokevirtual #291                // Method isPortalConnected:()Z
      14: invokevirtual #295                // Method net/minecraft/nbt/CompoundTag.putBoolean:(Ljava/lang/String;Z)V
      17: aload_2
      18: ldc_w         #269                // String color
      21: aload_0
      22: getfield      #28                 // Field color:I
      25: invokevirtual #277                // Method net/minecraft/nbt/CompoundTag.putInt:(Ljava/lang/String;I)V
      28: aload_2
      29: areturn

  public net.minecraft.network.protocol.game.ClientboundBlockEntityDataPacket getUpdatePacket();
    Code:
       0: aload_0
       1: invokestatic  #299                // Method net/minecraft/network/protocol/game/ClientboundBlockEntityDataPacket.create:(Lnet/minecraft/world/level/block/entity/BlockEntity;)Lnet/minecraft/network/protocol/game/ClientboundBlockEntityDataPacket;
       4: astore_1
       5: aload_1
       6: areturn

  public void onDataPacket(net.minecraft.network.Connection, net.minecraft.network.protocol.game.ClientboundBlockEntityDataPacket, net.minecraft.core.HolderLookup$Provider);
    Code:
       0: aload_0
       1: aload_2
       2: invokevirtual #305                // Method net/minecraft/network/protocol/game/ClientboundBlockEntityDataPacket.getTag:()Lnet/minecraft/nbt/CompoundTag;
       5: aload_3
       6: invokevirtual #309                // Method handleUpdateTag:(Lnet/minecraft/nbt/CompoundTag;Lnet/minecraft/core/HolderLookup$Provider;)V
       9: aload_0
      10: getfield      #1                  // Field level:Lnet/minecraft/world/level/Level;
      13: ifnull        36
      16: aload_0
      17: getfield      #1                  // Field level:Lnet/minecraft/world/level/Level;
      20: aload_0
      21: getfield      #312                // Field worldPosition:Lnet/minecraft/core/BlockPos;
      24: aload_0
      25: invokevirtual #91                 // Method getBlockState:()Lnet/minecraft/world/level/block/state/BlockState;
      28: aload_0
      29: invokevirtual #91                 // Method getBlockState:()Lnet/minecraft/world/level/block/state/BlockState;
      32: iconst_3
      33: invokevirtual #318                // Method net/minecraft/world/level/Level.sendBlockUpdated:(Lnet/minecraft/core/BlockPos;Lnet/minecraft/world/level/block/state/BlockState;Lnet/minecraft/world/level/block/state/BlockState;I)V
      36: return

  public void handleUpdateTag(net.minecraft.nbt.CompoundTag, net.minecraft.core.HolderLookup$Provider);
    Code:
       0: aload_0
       1: aload_1
       2: aload_2
       3: invokespecial #322                // Method net/minecraft/world/level/block/entity/BlockEntity.handleUpdateTag:(Lnet/minecraft/nbt/CompoundTag;Lnet/minecraft/core/HolderLookup$Provider;)V
       6: aload_0
       7: aload_1
       8: ldc_w         #289                // String connected
      11: invokevirtual #323                // Method net/minecraft/nbt/CompoundTag.getBoolean:(Ljava/lang/String;)Z
      14: putfield      #326                // Field clientIsConnected:Z
      17: aload_0
      18: aload_1
      19: ldc_w         #269                // String color
      22: invokevirtual #270                // Method net/minecraft/nbt/CompoundTag.getInt:(Ljava/lang/String;)I
      25: putfield      #28                 // Field color:I
      28: return

  public void setChanged();
    Code:
       0: aload_0
       1: invokespecial #330                // Method net/minecraft/world/level/block/entity/BlockEntity.setChanged:()V
       4: aload_0
       5: invokevirtual #91                 // Method getBlockState:()Lnet/minecraft/world/level/block/state/BlockState;
       8: invokestatic  #36                 // Method isPrimary:(Lnet/minecraft/world/level/block/state/BlockState;)Z
      11: ifeq          44
      14: aload_0
      15: getfield      #1                  // Field level:Lnet/minecraft/world/level/Level;
      18: ifnull        53
      21: aload_0
      22: getfield      #1                  // Field level:Lnet/minecraft/world/level/Level;
      25: aload_0
      26: getfield      #312                // Field worldPosition:Lnet/minecraft/core/BlockPos;
      29: aload_0
      30: invokevirtual #91                 // Method getBlockState:()Lnet/minecraft/world/level/block/state/BlockState;
      33: aload_0
      34: invokevirtual #91                 // Method getBlockState:()Lnet/minecraft/world/level/block/state/BlockState;
      37: iconst_2
      38: invokevirtual #318                // Method net/minecraft/world/level/Level.sendBlockUpdated:(Lnet/minecraft/core/BlockPos;Lnet/minecraft/world/level/block/state/BlockState;Lnet/minecraft/world/level/block/state/BlockState;I)V
      41: goto          53
      44: aload_0
      45: invokedynamic #187,  0            // InvokeDynamic #0:accept:()Ljava/util/function/Consumer;
      50: invokevirtual #224                // Method ifNeighborPresent:(Ljava/util/function/Consumer;)V
      53: return

  public static void serverTick(net.minecraft.world.level.Level, net.minecraft.core.BlockPos, net.minecraft.world.level.block.state.BlockState, io.redspace.ironsspellbooks.block.portal_frame.PortalFrameBlockEntity);
    Code:
       0: aload_0
       1: invokevirtual #331                // Method net/minecraft/world/level/Level.getGameTime:()J
       4: ldc2_w        #335                // long 5l
       7: lrem
       8: lconst_0
       9: lcmp
      10: ifne          25
      13: getstatic     #174                // Field io/redspace/ironsspellbooks/capabilities/magic/PortalManager.INSTANCE:Lio/redspace/ironsspellbooks/capabilities/magic/PortalManager;
      16: aload_3
      17: invokevirtual #133                // Method getUUID:()Ljava/util/UUID;
      20: bipush        -5
      22: invokevirtual #337                // Method io/redspace/ironsspellbooks/capabilities/magic/PortalManager.processCooldownTick:(Ljava/util/UUID;I)V
      25: aload_3
      26: getfield      #341                // Field active:Z
      29: ifeq          109
      32: aload_3
      33: aload_3
      34: dup
      35: getfield      #344                // Field activeCooldown:I
      38: iconst_1
      39: isub
      40: dup_x1
      41: putfield      #344                // Field activeCooldown:I
      44: ifle          51
      47: iconst_1
      48: goto          52
      51: iconst_0
      52: putfield      #341                // Field active:Z
      55: aload_0
      56: aconst_null
      57: checkcast     #228                // class net/minecraft/world/entity/Entity
      60: aload_2
      61: aload_0
      62: aload_1
      63: invokevirtual #347                // Method net/minecraft/world/level/block/state/BlockState.getShape:(Lnet/minecraft/world/level/BlockGetter;Lnet/minecraft/core/BlockPos;)Lnet/minecraft/world/phys/shapes/VoxelShape;
      66: invokevirtual #351                // Method net/minecraft/world/phys/shapes/VoxelShape.bounds:()Lnet/minecraft/world/phys/AABB;
      69: aload_1
      70: invokevirtual #357                // Method net/minecraft/world/phys/AABB.move:(Lnet/minecraft/core/BlockPos;)Lnet/minecraft/world/phys/AABB;
      73: aload_2
      74: invokevirtual #363                // Method net/minecraft/world/level/block/state/BlockState.getBlock:()Lnet/minecraft/world/level/block/Block;
      77: checkcast     #66                 // class io/redspace/ironsspellbooks/block/portal_frame/PortalFrameBlock
      80: dup
      81: invokestatic  #367                // Method java/util/Objects.requireNonNull:(Ljava/lang/Object;)Ljava/lang/Object;
      84: pop
      85: invokedynamic #372,  0            // InvokeDynamic #4:test:(Lio/redspace/ironsspellbooks/block/portal_frame/PortalFrameBlock;)Ljava/util/function/Predicate;
      90: invokevirtual #376                // Method net/minecraft/world/level/Level.getEntities:(Lnet/minecraft/world/entity/Entity;Lnet/minecraft/world/phys/AABB;Ljava/util/function/Predicate;)Ljava/util/List;
      93: aload_3
      94: dup
      95: invokestatic  #367                // Method java/util/Objects.requireNonNull:(Ljava/lang/Object;)Ljava/lang/Object;
      98: pop
      99: invokedynamic #380,  0            // InvokeDynamic #5:accept:(Lio/redspace/ironsspellbooks/block/portal_frame/PortalFrameBlockEntity;)Ljava/util/function/Consumer;
     104: invokeinterface #383,  2          // InterfaceMethod java/util/List.forEach:(Ljava/util/function/Consumer;)V
     109: return

  public void setActive();
    Code:
       0: aload_0
       1: iconst_1
       2: putfield      #341                // Field active:Z
       5: aload_0
       6: bipush        10
       8: putfield      #344                // Field activeCooldown:I
      11: return

  public int getColor();
    Code:
       0: aload_0
       1: invokevirtual #91                 // Method getBlockState:()Lnet/minecraft/world/level/block/state/BlockState;
       4: invokestatic  #36                 // Method isPrimary:(Lnet/minecraft/world/level/block/state/BlockState;)Z
       7: ifeq          15
      10: aload_0
      11: getfield      #28                 // Field color:I
      14: ireturn
      15: aload_0
      16: invokedynamic #388,  0            // InvokeDynamic #6:apply:()Ljava/util/function/Function;
      21: iconst_m1
      22: invokestatic  #389                // Method java/lang/Integer.valueOf:(I)Ljava/lang/Integer;
      25: invokevirtual #217                // Method ifNeighborPresentExecute:(Ljava/util/function/Function;Ljava/lang/Object;)Ljava/lang/Object;
      28: checkcast     #390                // class java/lang/Integer
      31: invokevirtual #395                // Method java/lang/Integer.intValue:()I
      34: ireturn

  private void setColor(int, boolean);
    Code:
       0: iload_1
       1: aload_0
       2: invokevirtual #399                // Method getColor:()I
       5: if_icmpeq     15
       8: aload_0
       9: invokevirtual #291                // Method isPortalConnected:()Z
      12: ifne          16
      15: return
      16: aload_0
      17: invokevirtual #91                 // Method getBlockState:()Lnet/minecraft/world/level/block/state/BlockState;
      20: invokestatic  #36                 // Method isPrimary:(Lnet/minecraft/world/level/block/state/BlockState;)Z
      23: ifeq          52
      26: aload_0
      27: iload_1
      28: putfield      #28                 // Field color:I
      31: aload_0
      32: invokevirtual #194                // Method setChanged:()V
      35: iload_2
      36: ifeq          62
      39: aload_0
      40: iload_1
      41: invokedynamic #402,  0            // InvokeDynamic #7:accept:(I)Ljava/util/function/Consumer;
      46: invokevirtual #190                // Method ifOtherPortalFramePresent:(Ljava/util/function/Consumer;)V
      49: goto          62
      52: aload_0
      53: iload_1
      54: invokedynamic #405,  0            // InvokeDynamic #8:accept:(I)Ljava/util/function/Consumer;
      59: invokevirtual #224                // Method ifNeighborPresent:(Ljava/util/function/Consumer;)V
      62: return

  public void setColor(int);
    Code:
       0: aload_0
       1: iload_1
       2: iconst_1
       3: invokevirtual #406                // Method setColor:(IZ)V
       6: return

  public net.minecraft.network.protocol.Packet getUpdatePacket();
    Code:
       0: aload_0
       1: invokevirtual #409                // Method getUpdatePacket:()Lnet/minecraft/network/protocol/game/ClientboundBlockEntityDataPacket;
       4: areturn

  private static void lambda$setColor$3(int, io.redspace.ironsspellbooks.block.portal_frame.PortalFrameBlockEntity);
    Code:
       0: aload_1
       1: iload_0
       2: invokevirtual #170                // Method setColor:(I)V
       5: return

  private static void lambda$setColor$2(int, io.redspace.ironsspellbooks.block.portal_frame.PortalFrameBlockEntity);
    Code:
       0: aload_1
       1: iload_0
       2: iconst_0
       3: invokevirtual #406                // Method setColor:(IZ)V
       6: return

  private void lambda$teleport$1(net.minecraft.server.level.ServerLevel, net.minecraft.world.entity.Entity, io.redspace.ironsspellbooks.entity.spells.portal.PortalPos);
    Code:
       0: aload_3
       1: invokevirtual #161                // Method io/redspace/ironsspellbooks/entity/spells/portal/PortalPos.pos:()Lnet/minecraft/world/phys/Vec3;
       4: astore        4
       6: aload_1
       7: aconst_null
       8: aload_0
       9: invokevirtual #87                 // Method getBlockPos:()Lnet/minecraft/core/BlockPos;
      12: getstatic     #413                // Field net/minecraft/sounds/SoundEvents.ENDERMAN_TELEPORT:Lnet/minecraft/sounds/SoundEvent;
      15: getstatic     #419                // Field net/minecraft/sounds/SoundSource.BLOCKS:Lnet/minecraft/sounds/SoundSource;
      18: fconst_1
      19: fconst_1
      20: invokevirtual #425                // Method net/minecraft/server/level/ServerLevel.playSound:(Lnet/minecraft/world/entity/player/Player;Lnet/minecraft/core/BlockPos;Lnet/minecraft/sounds/SoundEvent;Lnet/minecraft/sounds/SoundSource;FF)V
      23: aload_1
      24: invokevirtual #429                // Method net/minecraft/server/level/ServerLevel.dimension:()Lnet/minecraft/resources/ResourceKey;
      27: aload_3
      28: invokevirtual #149                // Method io/redspace/ironsspellbooks/entity/spells/portal/PortalPos.dimension:()Lnet/minecraft/resources/ResourceKey;
      31: invokevirtual #430                // Method java/lang/Object.equals:(Ljava/lang/Object;)Z
      34: ifeq          72
      37: aload_2
      38: aload_1
      39: aload         4
      41: getfield      #433                // Field net/minecraft/world/phys/Vec3.x:D
      44: aload         4
      46: getfield      #437                // Field net/minecraft/world/phys/Vec3.y:D
      49: aload         4
      51: getfield      #440                // Field net/minecraft/world/phys/Vec3.z:D
      54: getstatic     #443                // Field net/minecraft/world/entity/RelativeMovement.ROTATION:Ljava/util/Set;
      57: aload_3
      58: invokevirtual #449                // Method io/redspace/ironsspellbooks/entity/spells/portal/PortalPos.rotation:()F
      61: aload_2
      62: invokevirtual #453                // Method net/minecraft/world/entity/Entity.getXRot:()F
      65: invokevirtual #456                // Method net/minecraft/world/entity/Entity.teleportTo:(Lnet/minecraft/server/level/ServerLevel;DDDLjava/util/Set;FF)Z
      68: pop
      69: goto          153
      72: aload_1
      73: invokevirtual #129                // Method net/minecraft/server/level/ServerLevel.getServer:()Lnet/minecraft/server/MinecraftServer;
      76: astore        5
      78: aload         5
      80: aload_3
      81: invokevirtual #149                // Method io/redspace/ironsspellbooks/entity/spells/portal/PortalPos.dimension:()Lnet/minecraft/resources/ResourceKey;
      84: invokevirtual #155                // Method net/minecraft/server/MinecraftServer.getLevel:(Lnet/minecraft/resources/ResourceKey;)Lnet/minecraft/server/level/ServerLevel;
      87: astore        6
      89: aload         6
      91: ifnull        153
      94: aload_2
      95: new           #460                // class net/minecraft/world/level/portal/DimensionTransition
      98: dup
      99: aload         6
     101: aload         4
     103: getstatic     #462                // Field net/minecraft/world/phys/Vec3.ZERO:Lnet/minecraft/world/phys/Vec3;
     106: aload_3
     107: invokevirtual #449                // Method io/redspace/ironsspellbooks/entity/spells/portal/PortalPos.rotation:()F
     110: aload_2
     111: invokevirtual #453                // Method net/minecraft/world/entity/Entity.getXRot:()F
     114: getstatic     #466                // Field net/minecraft/world/level/portal/DimensionTransition.DO_NOTHING:Lnet/minecraft/world/level/portal/DimensionTransition$PostDimensionTransition;
     117: invokespecial #470                // Method net/minecraft/world/level/portal/DimensionTransition."<init>":(Lnet/minecraft/server/level/ServerLevel;Lnet/minecraft/world/phys/Vec3;Lnet/minecraft/world/phys/Vec3;FFLnet/minecraft/world/level/portal/DimensionTransition$PostDimensionTransition;)V
     120: invokevirtual #473                // Method net/minecraft/world/entity/Entity.changeDimension:(Lnet/minecraft/world/level/portal/DimensionTransition;)Lnet/minecraft/world/entity/Entity;
     123: pop
     124: aload         6
     126: aconst_null
     127: aload         4
     129: getfield      #433                // Field net/minecraft/world/phys/Vec3.x:D
     132: aload         4
     134: getfield      #437                // Field net/minecraft/world/phys/Vec3.y:D
     137: aload         4
     139: getfield      #440                // Field net/minecraft/world/phys/Vec3.z:D
     142: getstatic     #413                // Field net/minecraft/sounds/SoundEvents.ENDERMAN_TELEPORT:Lnet/minecraft/sounds/SoundEvent;
     145: getstatic     #419                // Field net/minecraft/sounds/SoundSource.BLOCKS:Lnet/minecraft/sounds/SoundSource;
     148: fconst_1
     149: fconst_1
     150: invokevirtual #477                // Method net/minecraft/server/level/ServerLevel.playSound:(Lnet/minecraft/world/entity/player/Player;DDDLnet/minecraft/sounds/SoundEvent;Lnet/minecraft/sounds/SoundSource;FF)V
     153: return

  private static void lambda$setOwnerUUID$0(java.util.UUID, io.redspace.ironsspellbooks.block.portal_frame.PortalFrameBlockEntity);
    Code:
       0: aload_1
       1: aload_0
       2: putfield      #32                 // Field ownerUUID:Ljava/util/UUID;
       5: return

  static net.minecraft.world.level.Level access$000(io.redspace.ironsspellbooks.block.portal_frame.PortalFrameBlockEntity);
    Code:
       0: aload_0
       1: getfield      #1                  // Field level:Lnet/minecraft/world/level/Level;
       4: areturn

  static net.minecraft.world.level.Level access$100(io.redspace.ironsspellbooks.block.portal_frame.PortalFrameBlockEntity);
    Code:
       0: aload_0
       1: getfield      #1                  // Field level:Lnet/minecraft/world/level/Level;
       4: areturn
}
